[{"chatter":"Nightbot","count":8050},{"chatter":"Lotharou","count":5686},{"chatter":"TheCrunge24","count":4875},{"chatter":"UVCW","count":4579},{"chatter":"Scyral","count":4255},{"chatter":"argyle_pigeon","count":4045},{"chatter":"Spazolin_Dirk","count":3588},{"chatter":"scifigirl211","count":3352},{"chatter":"sweatpantsandsuitjackets","count":3190},{"chatter":"beglebum","count":3188},{"chatter":"MynockGate","count":3148},{"chatter":"grindhaus","count":2851},{"chatter":"cysann","count":2371},{"chatter":"Teerizz","count":2299},{"chatter":"Ben64r","count":2192}]